{
  "PENDING_D1C8F2AE": {
    "id": "PENDING_D1C8F2AE",
    "full_name": "Laxmi",
    "office_email": "morishettylaxminivas@gmail.com",
    "organization": "nan",
    "mobile": "",
    "designation": "",
    "city": "",
    "state": "",
    "country": "",
    "linkedin": "",
    "website": "",
    "uploaded_at": "2025-12-31T04:56:37.843882",
    "status": "pending_invitation",
    "source": "bulk_upload",
    "invitation_sent": true,
    "invitation_sent_at": "2025-12-31T04:57:06.734638",
    "registration_complete": false,
    "registered_at": null,
    "is_org_only": false,
    "has_full_name": true,
    "invitation_token": "t3F_faYtBRJTiRn7KAN2ifpYOQp5J51mHQtXXB4Nb_E",
    "invitation_url": "http://127.0.0.1:5000/hr-registration?invite=t3F_faYtBRJTiRn7KAN2ifpYOQp5J51mHQtXXB4Nb_E"
  },
  "PENDING_838D802B": {
    "id": "PENDING_838D802B",
    "full_name": "Nivas",
    "office_email": "morishettymadan10@gmail.com",
    "organization": "nan",
    "mobile": "",
    "designation": "",
    "city": "",
    "state": "",
    "country": "",
    "linkedin": "",
    "website": "",
    "uploaded_at": "2025-12-31T04:56:37.844023",
    "status": "pending_invitation",
    "source": "bulk_upload",
    "invitation_sent": true,
    "invitation_sent_at": "2025-12-31T04:57:18.211153",
    "registration_complete": false,
    "registered_at": null,
    "is_org_only": false,
    "has_full_name": true,
    "invitation_token": "JpsH4iIkzVP4nsse06SjAuio8TJJkaHZFHFa2z69SmU",
    "invitation_url": "http://127.0.0.1:5000/hr-registration?invite=JpsH4iIkzVP4nsse06SjAuio8TJJkaHZFHFa2z69SmU"
  },
  "PENDING_D73418E4": {
    "id": "PENDING_D73418E4",
    "full_name": "Morishetty",
    "office_email": "laxminivasmorishetty143@gmail.com",
    "organization": "nan",
    "mobile": "",
    "designation": "",
    "city": "",
    "state": "",
    "country": "",
    "linkedin": "",
    "website": "",
    "uploaded_at": "2025-12-31T04:56:37.844131",
    "status": "pending_invitation",
    "source": "bulk_upload",
    "invitation_sent": true,
    "invitation_sent_at": "2025-12-31T04:57:24.111623",
    "registration_complete": false,
    "registered_at": null,
    "is_org_only": false,
    "has_full_name": true,
    "invitation_token": "gHHY7zhf1d_2aTHyOFUdeT2OGFi3mgx7VBjSBF0OEk8",
    "invitation_url": "http://127.0.0.1:5000/hr-registration?invite=gHHY7zhf1d_2aTHyOFUdeT2OGFi3mgx7VBjSBF0OEk8"
  }
}